{"cameraMode":{"drawMode":0,"name":"Shaded","section":"Shading Mode"},"sceneLighting":true,"audioPlay":false,"sceneViewState":{"m_AlwaysRefresh":false,"showFog":true,"showSkybox":true,"showFlares":true,"showImageEffects":true,"showParticleSystems":true,"showVisualEffectGraphs":true,"m_FxEnabled":true},"in2DMode":false,"pivot":{"x":1.399999976158142,"y":-0.25728487968444826,"z":3.939026355743408},"rotation":{"x":-0.3441257178783417,"y":-0.003663555486127734,"z":0.0013431657571345568,"w":-0.9389205574989319},"size":6.448493480682373,"orthographic":false}